{"Nodes":[],"ExecutionTime":"2023-11-17T01:29:41.5400048Z","GenerationTime":"0001-01-01T00:00:00","PluginUserSpecFlowId":"6b1d3fcb-c14d-4dc1-a04d-2e19c70d1158","CLIUserSpecFlowId":null,"ExecutionResults":[{"ContextType":"Scenario","FeatureFolderPath":"Features","FeatureTitle":"This test suite contains scenarios for Profile Page Language feature","ScenarioTitle":"H. Adding a Existing Language","ScenarioArguments":[],"Status":"TestError","StepResults":[{"Duration":"00:00:08.3564766","Status":"OK","Error":null,"Outputs":null},{"Duration":"00:00:06.4024616","Status":"OK","Error":null,"Outputs":null},{"Duration":"00:00:03.1116984","Status":"TestError","Error":"This language is already exist in your language list.","Outputs":null}],"Outputs":null}],"StepReports":null}